Workbook

Sheet Summary 摘要
A1: HKEX 文件資料萃取報告
A2: Automated Extraction Report — Business Valuation Support
A4: 來源文件 Source file | B4: 00060_HK_FOOD_INV_20260729.pdf
A5: 產生時間 Generated | B5: 2026-08-30 22:16
A7: 總頁數 Total pages | B7: 142
A8: 已擷取字元 Characters extracted | B8: 339740
A9: 含表格頁數 Pages with tables | B9: 0
A10: 需人手/OCR 頁數 Pages needing OCR | B10: 2
A12: 估值參數擷取筆數 Valuation parameters | B12: 7
A13: 財務科目擷取筆數 Financial line items | B13: 17
A14: 主題段落擷取筆數 Topic extracts | B14: 77
A15: AI 複核筆數 AI-verified findings | B15: 0
A17: 資料完整性檢查 Integrity checks
A18: 用會計恆等式交叉驗證擷取結果 —— 數字之間本來就該對得上,對不上代表某欄可能抓錯,請翻回來源頁核對。
A19: ✓ 流動資產 − 流動負債 = 淨流動資產 | B19: 152,893 − 36,903 = 115,990
A20: ✓ 收入 − 銷售成本 = 毛利 | B20: 158,329 − 143,063 = 15,266 vs 毛利 15,266
A21: ✓ 除稅前溢利 ± 稅項 = 年內溢利 | B21: -17,537 + 772 = -18,309 vs -18,309
A22: ✓ 三大報表應相鄰 | B22: Income Statement: p.55、Balance Sheet: p.57、Cash Flow: p.61(相距 6 頁)
A24: 方法論 Methodology
A25: 1. 逐頁擷取文字,全程保留 PDF 頁碼與年報印刷頁碼(可追溯性)。
A26: 2. 規則層(正則/關鍵字)先把全份文件縮減為少數相關頁面 —— 解決「文件太大」。
A27: 3. 數字由正則精確擷取並做合理性檢查,不由語言模型生成 —— 解決「準確度」。
A28: 4. AI 僅在縮減後的頁面上做語意判斷,且輸出頁碼須通過驗證才保留。
A29: 5. 所有結果附來源頁碼與原文行,供估值師覆核。信心度為 Low 者建議人手確認。
A30: 6. 支援中英對照年報、破折號(nil)、Profit/(loss) 等港股常見排版。

Sheet Valuation Params 估值參數
A1: 估值參數 Benchmark — 可直接併入行內參數資料庫
A2: 數字由正則式從原文精確擷取,並經合理範圍檢查;非由 AI 生成。
A4: 參數 Parameter | B4: 中文 | C4: 下限 Low (%) | D4: 上限 High (%) | E4: 原文數值 | F4: 信心度 | G4: 來源頁 Source Page | H4: 上下文 Context
A5: Discount Rate | B5: 折現率 | C5: 10 | D5: 10 | E5: 10% | F5: High | G5: PDF p.106 (印刷頁 105) | H5: 算的現金流量預測。現金流量 cash-generating units are determined based on value-in-use 預測採用的稅前貼現率為10%。 calculations using cash flow projections based on financial budgets covering a period of the remaining lease terms. The pre-tax discount rate applied for
A6: Discount Rate | B6: 折現率 | C6: 12.8 | D6: 12.8 | E6: 12.8% | F6: High | G6: PDF p.111 (印刷頁 110) | H6: g a five-year period approved by 算。現金流預測所使用之貼現率為11.5%（二零 senior management. The discount rate applied to the cash flow 二五年：12.8%）。超過五年期間之現金產生單 projection is 11.5% (2025: 12.8%). The growth rate used to 位之現金流增長率預測為2.0%（二零二五年： extrapolate the cash flows o
A7: Discount Rate | B7: 折現率 | C7: 11.5 | D7: 11.5 | E7: 11.5% | F7: High | G7: PDF p.111 (印刷頁 110) | H7: 用現金流預測計 on financial budgets covering a five-year period approved by 算。現金流預測所使用之貼現率為11.5%（二零 senior management. The discount rate applied to the cash flow 二五年：12.8%）。超過五年期間之現金產生單 projection is 11.5% (2025: 12.8%). The growth rate used to 位之現金流
A8: Gross Margin | B8: 毛利率 | C8: 9.6 | D8: 9.6 | E8: (%) 9.6 | F8: Medium | G8: PDF p.13 (印刷頁 12) | H8: ch 截至三月三十一日止年度 2026 2025 二零二六年 二零二五年 Revenue (HK$’000) 收入（港幣千元） 158,329 186,787 Gross profit margin (%)(1) 毛利率（百分比）(1) 9.6 15.0 Trade receivables turnover (days)(2) 應收貿易賬款周轉（天數）(2) 31 33 Inventory turnover (days)(3) 存貨周轉（天數）(3) 84 92 Operating expenses to sal
A9: Gross Margin | B9: 毛利率 | C9: 9.6 | D9: 9.6 | E9: 9.6% | F9: High | G9: PDF p.14 (印刷頁 13) | H9: Discussion and Analysis 管理層討論及分析 13 Gross Profit Margin 毛利率 The Group’s overall gross profit margin compressed to 9.6% from 集團整體毛利率由上一財政年度的15.0%收窄至本年 15.0% in the previous financial year. This contraction was primarily 度的9.6%。此降幅主要受貿易業務所拖累，該分部 driven by the t
A10: Gross Margin | B10: 毛利率 | C10: 67.1 | D10: 71 | E10: 67.1% to 71.0% | F10: High | G10: PDF p.14 (印刷頁 13) | H10: thin a challenging 利率顯著下降。 economic climate. Conversely, the catering segment’s gross profit margin improved from 相反，餐飲業務的毛利率由67.1%上升至71.0%，反 67.1% to 71.0%, reflecting the successful implementation of stringent 映了實施嚴格成本控制及有效廚餘管理的成功。然 cost control protocols a
A11: Gross Margin | B11: 毛利率 | C11: 15 | D11: 15 | E11: 15.0% | F11: High | G11: PDF p.14 (印刷頁 13) | H11: Margin 毛利率 The Group’s overall gross profit margin compressed to 9.6% from 集團整體毛利率由上一財政年度的15.0%收窄至本年 15.0% in the previous financial year. This contraction was primarily 度的9.6%。此降幅主要受貿易業務所拖累，該分部 driven by the trading segment, where the gross

Sheet Financials 財務數據
A1: 三大報表擷取結果
A2: 偵測到的年度欄位 — Income Statement: 2026 / 2025; Balance Sheet: 2026 / 2025; Cash Flow: 2026 / 2025
A4: 報表 Statement | B4: 科目 Item | C4: 本年 Current | D4: 上年 Prior | E4: 變動 YoY % | F4: 來源頁 | G4: 原文行 Source line
A5: Income Statement | B5: Revenue | C5: 158329 | D5: 186787 | E5: =IF(ISERROR((C5-D5)/ABS(D5)),"",(C5-D5)/ABS(D5)) -> -0.15235536 | F5: PDF p.55 (印刷頁 54) | G5: REVENUE 收入 5 158,329 186,787
A6: Income Statement | B6: Cost of Sales | C6: -143063 | D6: -158703 | E6: =IF(ISERROR((C6-D6)/ABS(D6)),"",(C6-D6)/ABS(D6)) -> 0.098548862 | F6: PDF p.55 (印刷頁 54) | G6: Cost of sales 銷售成本 (143,063) (158,703)
A7: Income Statement | B7: Gross Profit | C7: 15266 | D7: 28084 | E7: =IF(ISERROR((C7-D7)/ABS(D7)),"",(C7-D7)/ABS(D7)) -> -0.45641646 | F7: PDF p.55 (印刷頁 54) | G7: Gross profit 毛利 15,266 28,084
A8: Income Statement | B8: Finance Costs | C8: -1060 | D8: -1720 | E8: =IF(ISERROR((C8-D8)/ABS(D8)),"",(C8-D8)/ABS(D8)) -> 0.38372093 | F8: PDF p.55 (印刷頁 54) | G8: Finance costs 融資成本 6 (1,060) (1,720)
A9: Income Statement | B9: Profit Before Tax | C9: -17537 | D9: -18443 | E9: =IF(ISERROR((C9-D9)/ABS(D9)),"",(C9-D9)/ABS(D9)) -> 0.049124329 | F9: PDF p.55 (印刷頁 54) | G9: LOSS BEFORE TAX 除稅前虧損 7 (17,537) (18,443)
A10: Income Statement | B10: Income Tax | C10: -772 | D10: -909 | E10: =IF(ISERROR((C10-D10)/ABS(D10)),"",(C10-D10)/ABS(D10)) -> 0.15071507 | F10: PDF p.55 (印刷頁 54) | G10: Income tax expense 所得稅開支 10 (772) (909)
A11: Income Statement | B11: Profit for the Year | C11: -18309 | D11: -19352 | E11: =IF(ISERROR((C11-D11)/ABS(D11)),"",(C11-D11)/ABS(D11)) -> 0.053896238 | F11: PDF p.55 (印刷頁 54) | G11: LOSS FOR THE YEAR 本年度虧損 (18,309) (19,352)
A12: Balance Sheet | B12: Property Plant and Equipment | C12: 14436 | D12: 37224 | E12: =IF(ISERROR((C12-D12)/ABS(D12)),"",(C12-D12)/ABS(D12)) -> -0.61218569 | F12: PDF p.57 (印刷頁 56) | G12: Property, plant and equipment 物業、廠房及設備 12 14,436 37,224
A13: Balance Sheet | B13: Goodwill | C13: 2103 | D13: 2103 | E13: =IF(ISERROR((C13-D13)/ABS(D13)),"",(C13-D13)/ABS(D13)) -> 0 | F13: PDF p.57 (印刷頁 56) | G13: Goodwill 商譽 15 2,103 2,103
A14: Balance Sheet | B14: Inventories | C14: 29384 | D14: 36453 | E14: =IF(ISERROR((C14-D14)/ABS(D14)),"",(C14-D14)/ABS(D14)) -> -0.19392094 | F14: PDF p.57 (印刷頁 56) | G14: Inventories 存貨 17 29,384 36,453
A15: Balance Sheet | B15: Trade Receivables | C15: 11558 | D15: 15520 | E15: =IF(ISERROR((C15-D15)/ABS(D15)),"",(C15-D15)/ABS(D15)) -> -0.25528351 | F15: PDF p.57 (印刷頁 56) | G15: Trade receivables 應收貿易賬款 18 11,558 15,520
A16: Balance Sheet | B16: Cash and Equivalents | C16: 66523 | D16: 80294 | E16: =IF(ISERROR((C16-D16)/ABS(D16)),"",(C16-D16)/ABS(D16)) -> -0.17150721 | F16: PDF p.57 (印刷頁 56) | G16: Cash and cash equivalents 現金及現金等值項目 21 66,523 80,294
... A21: Cash Flow | B21: Financing Cash Flow | C21: -17546 | D21: -12848 | E21: =IF(ISERROR((C21-D21)/ABS(D21)),"",(C21-D21)/ABS(D21)) -> -0.36566002 | F21: PDF p.62 (印刷頁 61) | G21: Net cash flows used in financing activities 融資活動之現金流出淨額 (17,546) (12,848)
A23: 藍色 = 從 PDF 原文擷取的數值(硬輸入);黑色 = 公式計算。單位依原報表所示(通常為千元或百萬元),請對照來源頁確認。

Sheet Ratios 財務比率
A1: 衍生比率 — 全部以公式連結至 Financials 分頁
A2: 改動 Financials 分頁的數字,本頁會自動重算。
A4: 比率 Ratio | B4: 本年 Current | C4: 上年 Prior | D4: 說明
A5: Gross Margin 毛利率 | B5: =IF(ISERROR(INDEX('Financials 財務數據'!$C$5:$C$21,MATCH("Gross Profit",'Financials 財務數據'!$B$5:$B$21,0))/INDEX('Financials 財務數據'!$C$5:$C$21,MATCH("Revenue",'Financials 財務數據'!$B$5:$B$21,0))),"n/a",INDEX('Financials 財務數據'!$C$5:$C$21,MATCH("Gross Profit",'Financials 財務數據'!$B$5:$B$21,0))/INDEX('Financials 財務數據'!$C$5:$C$21,MATCH("Revenue",'Financials 財務數據'!$B$5:$B$21,0))) -> 0.096419481 | C5: =IF(ISERROR(INDEX('Financials 財務數據'!$D$5:$D$21,MATCH("Gross Profit",'Financials 財務數據'!$B$5:$B$21,0))/INDEX('Financials 財務數據'!$D$5:$D$21,MATCH("Revenue",'Financials 財務數據'!$B$5:$B$21,0))),"n/a",INDEX('Financials 財務數據'!$D$5:$D$21,MATCH("Gross Profit",'Financials 財務數據'!$B$5:$B$21,0))/INDEX('Financials 財務數據'!$D$5:$D$21,MATCH("Revenue",'Financials 財務數據'!$B$5:$B$21,0))) -> 0.15035308 | D5: 毛利 ÷ 收入
A6: Net Margin 淨利率 | B6: =IF(ISERROR(INDEX('Financials 財務數據'!$C$5:$C$21,MATCH("Profit for the Year",'Financials 財務數據'!$B$5:$B$21,0))/INDEX('Financials 財務數據'!$C$5:$C$21,MATCH("Revenue",'Financials 財務數據'!$B$5:$B$21,0))),"n/a",INDEX('Financials 財務數據'!$C$5:$C$21,MATCH("Profit for the Year",'Financials 財務數據'!$B$5:$B$21,0))/INDEX('Financials 財務數據'!$C$5:$C$21,MATCH("Revenue",'Financials 財務數據'!$B$5:$B$21,0))) -> -0.11563895 | C6: =IF(ISERROR(INDEX('Financials 財務數據'!$D$5:$D$21,MATCH("Profit for the Year",'Financials 財務數據'!$B$5:$B$21,0))/INDEX('Financials 財務數據'!$D$5:$D$21,MATCH("Revenue",'Financials 財務數據'!$B$5:$B$21,0))),"n/a",INDEX('Financials 財務數據'!$D$5:$D$21,MATCH("Profit for the Year",'Financials 財務數據'!$B$5:$B$21,0))/INDEX('Financials 財務數據'!$D$5:$D$21,MATCH("Revenue",'Financials 財務數據'!$B$5:$B$21,0))) -> -0.10360464 | D6: 年內溢利 ÷ 收入
A7: Current Ratio 流動比率 | B7: =IF(ISERROR(INDEX('Financials 財務數據'!$C$5:$C$21,MATCH("Total Current Assets",'Financials 財務數據'!$B$5:$B$21,0))/INDEX('Financials 財務數據'!$C$5:$C$21,MATCH("Total Current Liabilities",'Financials 財務數據'!$B$5:$B$21,0))),"n/a",INDEX('Financials 財務數據'!$C$5:$C$21,MATCH("Total Current Assets",'Financials 財務數據'!$B$5:$B$21,0))/INDEX('Financials 財務數據'!$C$5:$C$21,MATCH("Total Current Liabilities",'Financials 財務數據'!$B$5:$B$21,0))) -> 4.1431049 | C7: =IF(ISERROR(INDEX('Financials 財務數據'!$D$5:$D$21,MATCH("Total Current Assets",'Financials 財務數據'!$B$5:$B$21,0))/INDEX('Financials 財務數據'!$D$5:$D$21,MATCH("Total Current Liabilities",'Financials 財務數據'!$B$5:$B$21,0))),"n/a",INDEX('Financials 財務數據'!$D$5:$D$21,MATCH("Total Current Assets",'Financials 財務數據'!$B$5:$B$21,0))/INDEX('Financials 財務數據'!$D$5:$D$21,MATCH("Total Current Liabilities",'Financials 財務數據'!$B$5:$B$21,0))) -> 2.6908758 | D7: 流動資產 ÷ 流動負債
A8: Debt / Equity 負債權益比 | B8: =IF(ISERROR(INDEX('Financials 財務數據'!$C$5:$C$21,MATCH("Total Liabilities",'Financials 財務數據'!$B$5:$B$21,0))/INDEX('Financials 財務數據'!$C$5:$C$21,MATCH("Total Equity",'Financials 財務數據'!$B$5:$B$21,0))),"n/a",INDEX('Financials 財務數據'!$C$5:$C$21,MATCH("Total Liabilities",'Financials 財務數據'!$B$5:$B$21,0))/INDEX('Financials 財務數據'!$C$5:$C$21,MATCH("Total Equity",'Financials 財務數據'!$B$5:$B$21,0))) -> n/a | C8: =IF(ISERROR(INDEX('Financials 財務數據'!$D$5:$D$21,MATCH("Total Liabilities",'Financials 財務數據'!$B$5:$B$21,0))/INDEX('Financials 財務數據'!$D$5:$D$21,MATCH("Total Equity",'Financials 財務數據'!$B$5:$B$21,0))),"n/a",INDEX('Financials 財務數據'!$D$5:$D$21,MATCH("Total Liabilities",'Financials 財務數據'!$B$5:$B$21,0))/INDEX('Financials 財務數據'!$D$5:$D$21,MATCH("Total Equity",'Financials 財務數據'!$B$5:$B$21,0))) -> n/a | D8: 總負債 ÷ 總權益
A9: Goodwill / Total Assets | B9: =IF(ISERROR(INDEX('Financials 財務數據'!$C$5:$C$21,MATCH("Goodwill",'Financials 財務數據'!$B$5:$B$21,0))/INDEX('Financials 財務數據'!$C$5:$C$21,MATCH("Total Assets",'Financials 財務數據'!$B$5:$B$21,0))),"n/a",INDEX('Financials 財務數據'!$C$5:$C$21,MATCH("Goodwill",'Financials 財務數據'!$B$5:$B$21,0))/INDEX('Financials 財務數據'!$C$5:$C$21,MATCH("Total Assets",'Financials 財務數據'!$B$5:$B$21,0))) -> n/a | C9: =IF(ISERROR(INDEX('Financials 財務數據'!$D$5:$D$21,MATCH("Goodwill",'Financials 財務數據'!$B$5:$B$21,0))/INDEX('Financials 財務數據'!$D$5:$D$21,MATCH("Total Assets",'Financials 財務數據'!$B$5:$B$21,0))),"n/a",INDEX('Financials 財務數據'!$D$5:$D$21,MATCH("Goodwill",'Financials 財務數據'!$B$5:$B$21,0))/INDEX('Financials 財務數據'!$D$5:$D$21,MATCH("Total Assets",'Financials 財務數據'!$B$5:$B$21,0))) -> n/a | D9: 商譽佔總資產比重 — 減值風險指標
A10: Intangibles / Total Assets | B10: =IF(ISERROR(INDEX('Financials 財務數據'!$C$5:$C$21,MATCH("Intangible Assets",'Financials 財務數據'!$B$5:$B$21,0))/INDEX('Financials 財務數據'!$C$5:$C$21,MATCH("Total Assets",'Financials 財務數據'!$B$5:$B$21,0))),"n/a",INDEX('Financials 財務數據'!$C$5:$C$21,MATCH("Intangible Assets",'Financials 財務數據'!$B$5:$B$21,0))/INDEX('Financials 財務數據'!$C$5:$C$21,MATCH("Total Assets",'Financials 財務數據'!$B$5:$B$21,0))) -> n/a | C10: =IF(ISERROR(INDEX('Financials 財務數據'!$D$5:$D$21,MATCH("Intangible Assets",'Financials 財務數據'!$B$5:$B$21,0))/INDEX('Financials 財務數據'!$D$5:$D$21,MATCH("Total Assets",'Financials 財務數據'!$B$5:$B$21,0))),"n/a",INDEX('Financials 財務數據'!$D$5:$D$21,MATCH("Intangible Assets",'Financials 財務數據'!$B$5:$B$21,0))/INDEX('Financials 財務數據'!$D$5:$D$21,MATCH("Total Assets",'Financials 財務數據'!$B$5:$B$21,0))) -> n/a | D10: 無形資產佔比
A11: ROE 股本回報率 | B11: =IF(ISERROR(INDEX('Financials 財務數據'!$C$5:$C$21,MATCH("Profit for the Year",'Financials 財務數據'!$B$5:$B$21,0))/INDEX('Financials 財務數據'!$C$5:$C$21,MATCH("Total Equity",'Financials 財務數據'!$B$5:$B$21,0))),"n/a",INDEX('Financials 財務數據'!$C$5:$C$21,MATCH("Profit for the Year",'Financials 財務數據'!$B$5:$B$21,0))/INDEX('Financials 財務數據'!$C$5:$C$21,MATCH("Total Equity",'Financials 財務數據'!$B$5:$B$21,0))) -> -0.035572385 | C11: =IF(ISERROR(INDEX('Financials 財務數據'!$D$5:$D$21,MATCH("Profit for the Year",'Financials 財務數據'!$B$5:$B$21,0))/INDEX('Financials 財務數據'!$D$5:$D$21,MATCH("Total Equity",'Financials 財務數據'!$B$5:$B$21,0))),"n/a",INDEX('Financials 財務數據'!$D$5:$D$21,MATCH("Profit for the Year",'Financials 財務數據'!$B$5:$B$21,0))/INDEX('Financials 財務數據'!$D$5:$D$21,MATCH("Total Equity",'Financials 財務數據'!$B$5:$B$21,0))) -> -0.036706297 | D11: 年內溢利 ÷ 總權益
A13: 顯示 "n/a" 表示該科目未在文件中成功擷取,需人手補入。

Sheet Chart 趨勢圖
A1: 本年 vs 上年 — 主要科目比較
A2: 港交所主板及 GEM 自 2024 年起均無強制季度報告,故以年度 / 中期數據作趨勢比較較符合披露實況。
A4: Item | B4: Prior | C4: Current
A5: Revenue | B5: 186787 | C5: 158329
A6: Gross Profit | B6: 28084 | C6: 15266
A7: Profit Before Tax | B7: -18443 | C7: -17537
A8: Profit for the Year | B8: -19352 | C8: -18309
A9: Total Equity | B9: 527212 | C9: 514697

Sheet Extracts 主題段落
A1: 主題式段落擷取 — 供估值師快速定位原文
A3: 主題 Topic | B3: 中文 | C3: 優先 | D3: 命中詞 | E3: 來源頁 | F3: 段落 Snippet
A4: Fair Value Measurement | B4: 公允價值計量 | C4: high | D4: 公允價值 | E4: PDF p.68 (印刷頁 67) | F4: res. Moreover, the amendments clarify the 資產和合同關聯工具的分類要求。這些修訂還 requirements for classifying financial assets with non-recourse 包括對指定以公允價值計量且其變動計入其他 features and contractually linked instruments. The amendments 綜合收益的權益工具投資以及具有條件特徵的 also include additional disclosures for investments in equity 金融工具的額外披露要求。這些修訂應追溯應 instruments designated at fair value through other comprehensive 用，並在首次應用日期對期初留存收益（或權 income and financial instruments with contingent features. The 益的其他組成部分）進行調整。不要求重述前 amendments shall be applied retrospectively with
A5: Fair Value Measurement | B5: 公允價值計量 | C5: high | D5: fair value hierarchy | E5: PDF p.73 (印刷頁 72) | F5: fair value is measured or 所有載於本財務報告計量或披露的資產及負債 disclosed in the financial statements are categorised within the 乃基於對公平值計量整體而言屬重大的最低層 fair value hierarchy, described as follows, based on the lowest 輸入數據按以下公平值架構分類： level input that is significant to the fair value measurement as a whole: Level 1 – based on quoted prices (unadjusted) in active 第一級 – 基於相同資產或負債於活躍巿 markets for identical assets or liabilities 場的報價（未經調整） Level 2 – based on valuation techniques for which the lowest 第二級 – 基於對公平值計量而言屬重大 level input that is significant to
A6: Fair Value Measurement | B6: 公允價值計量 | C6: high | D6: level 1 | E6: PDF p.110 (印刷頁 109) | F6: March 2026 using 於二零二六年三月三十一日之 公平值計量採用 Quoted price in Significant Significant active observable unobservable market inputs inputs (Level 1) (Level 2) (Level 3) Total 活躍市場 重大可觀察 重大不可 報價 輸入值 觀察輸入值 （第一層） （第二層） （第三層） 總計 HK$’000 HK$’000 HK$’000 HK$’000 港幣千元 港幣千元 港幣千元 港幣千元 Commercial 商用 – – 13,394 13,394 Fair value measurement as at 31 March 2025 using 於二零二五年三月三十一日之 公平值計量採用 Quoted price in Significant Significant active observable unobservable market inputs inputs (Level 1) (Level 2) (Level 3) Total 活躍市場 重大可觀察 重大不可 報價 輸入值 觀察輸入值 （第一
A7: Fair Value Measurement | B7: 公允價值計量 | C7: high | D7: unobservable input | E7: PDF p.111 (印刷頁 110) | F7: es used and the key 下文載列投資物業估值所用之估值方法及主要 inputs to the valuation of the investment property: 輸入值之概要： Significant Valuation technique unobservable inputs Weighted average 估值方法 重大不可觀察輸入值 加權平均數 Commercial property in Japan Direct comparison approach Estimated market value JPY6,608,000 (per square metre) 6,608,000日圓 (2025: JPY6,030,000) 於日本之商用物業 直接比較法 估計市值（每平方米） （二零二五年： 6,030,000日圓） Further particulars of the Group’s investment property are 有關本集團投資物業之進一步資料載於年報第 included on page 140 of the annual report. 140頁。 15. GOODWILL 15. 商譽 HK
A8: Fair Value Measurement | B8: 公允價值計量 | C8: high | D8: fair value hierarchy | E8: PDF p.131 (印刷頁 130) | F8: Notes to Financial Statements 130 財務報告附註 31 March 2026 二零二六年三月三十一日 32. FAIR VALUE AND FAIR VALUE HIERARCHY OF 32. 金融工具之公平值及公平值層級 FINANCIAL INSTRUMENTS The Group’s financial assets at fair value through profit or loss 本集團之按公平值透過損益入賬之金融資產乃 were carried at fair value. 按公平值列賬。 Management has assessed that the fair values of cash and 管理層已評估，現金及現金等值項目、應收貿 cash equivalents, trade receivables, trade and bills payables, 易賬款、應付貿易賬款及票據、包括於預付款 financial assets included in prepayments, deposits
A9: Fair Value Measurement | B9: 公允價值計量 | C9: high | D9: fair value hierarchy | E9: PDF p.132 (印刷頁 131) | F9: Notes to Financial Statements 財務報告附註 131 31 March 2026 二零二六年三月三十一日 32. FAIR VALUE AND FAIR VALUE HIERARCHY OF 32. 金融工具之公平值及公平值層級（續） FINANCIAL INSTRUMENTS (continued) Fair value hierarchy 公平值架構 The following tables illustrate the fair value measurement 下表顯示本集團金融工具的公平值計量架構： hierarchy of the Group’s financial instruments: Assets measured at fair value: 按公平值計量的資產： As at 31 March 2026 於二零二六年三月三十一日 Fair value measurement using 公平值計量採用 Quoted prices Significant Significant in active obser
A10: Fair Value Measurement | B10: 公允價值計量 | C10: high | D10: fair value hierarchy | E10: PDF p.133 (印刷頁 132) | F10: Notes to Financial Statements 132 財務報告附註 31 March 2026 二零二六年三月三十一日 32. FAIR VALUE AND FAIR VALUE HIERARCHY OF 32. 金融工具之公平值及公平值層級（續） FINANCIAL INSTRUMENTS (continued) Fair value hierarchy (continued) 公平值架構（續） Assets measured at fair value: (continued) 按公平值計量的資產：（續） The movements in fair value measurements within Level 3 during 年內屬於第三層之公平值計量之變動如下： the year are as follows: Equity investments at fair value through profit or loss 按公平值透過損益入賬之權益投資 2026 2025 二零二六年 二零二五年 HK$’000 HK$’000 港幣千
A11: Impairment Testing | B11: 減值測試 | C11: high | D11: impairment test | E11: PDF p.51 (印刷頁 50) | F11: 貼現現金流量預測並進行敏 whether any impairment was required for the investment in 感性分析。我們其後將貼現現金流量預測之可收回金額與 FSMHL Group. For the purpose of the impairment test, the 賬面金額進行比較。我們已加入我們的內部估值專家協助 recoverable amount of the FSMHL Group was determined 我們評估用於釐定FSMHL集團可收回金額的方法及貼現率。 based on a value-in-use calculation using estimated cash flow forecast based on financial budgets applied with the suitable growth rate and discount rate. 於報告期末，管理層已評估於FSMHL集團之投資是否需要 減值處理。就減值測試而言，FSMHL集團的可收回金額乃 根據使用價值計算，使用根據應用適當增長率及貼現率的 財務預算作出的估計現金流量預測釐定。 The impairment
A12: Impairment Testing | B12: 減值測試 | C12: high | D12: impairment loss | E12: PDF p.71 (印刷頁 70) | F12: osition at the Group’s share 淨額按權益法計算減去任何減值損失，列入本 of net assets under the equity method of accounting, less any 集團綜合財務狀況表內。任何可能存在的相異 impairment losses. Adjustments are made to bring into line any 會計政策已作出相應調整使之貫徹一致。本集 dissimilar accounting policies that may exist. The Group’s share 團應佔聯營公司之收購後業績及其他全面收益 of the post-acquisition results and other comprehensive income 分別計入綜合損益表及綜合其他全面收益。此 of associates is included in the consolidated statement of profit or 外，當於聯營公司之股權直接確認變動時，本 loss and consolidated other comprehensive income, respec
A13: Impairment Testing | B13: 減值測試 | C13: high | D13: impairment test | E13: PDF p.72 (印刷頁 71) | F13: 變動而顯示賬面值可能有損，則須更頻 circumstances indicate that the carrying value may be impaired. 密地作減值測試。本集團會於每年三月三十一 The Group performs its annual impairment test of goodwill as at 日進行減值測試。為了進行減值測試，因業務 31 March. For the purpose of impairment testing, goodwill 合併而購入的商譽自購入之日被分配至預期可 acquired in a business combination is, from the acquisition date, 從合併產生的協同效益中獲益的本集團各個現 allocated to each of the Group’s cash-generating units, or groups 金產生單位或現金產生單位組別，而無論本集 of cash-generating units, that are expected to benefit from the 團其他資產或負債是否已分配予該等單位或單 synergi
A14: Impairment Testing | B14: 減值測試 | C14: high | D14: cash-generating unit | E14: PDF p.73 (印刷頁 72) | F14: POLICIES (continued) 2.4 重大會計政策（續） Business combinations and goodwill (continued) 業務合併及商譽（續） Where goodwill has been allocated to a cash-generating unit 當商譽構成一個現金產生單元（或現金產生單 (or group of cash-generating units) and part of the operation 元之組別）的一部份而該單元的某部份業務被 within that unit is disposed of, the goodwill associated with the 出售，並在決定出售業務的損益時，與出售業 operation disposed of is included in the carrying amount of the 務相關的商譽將包括在該業務的賬面值內。在 operation when determining the gain or loss on the disposal. 此情況下出售的商譽將以出售業務和現金產生 Goodwill disposed of
... A80: Related Party Transactions | B80: 關聯方交易 | C80: low | D80: related party | E80: PDF p.129 (印刷頁 128) | F80: Notes to Financial Statements 128 財務報告附註 31 March 2026 二零二六年三月三十一日 30. RELATED PARTY TRANSACTIONS (continued) 30. 關連人士交易（續） (c) Compensation of key management personnel of the (c) 本集團主要管理人員之報酬： Group: 2026 2025 二零二六年 二零二五年 HK$’000 HK$’000 港幣千元 港幣千元 Short term employee benefits 短期僱員福利 6,129 6,020 Pension scheme contributions 退休金計劃之供款 73 70 Total compensation paid to key 已向主要管理人員支付之 management personnel 報酬總額 6,202 6,090 Further details of directors’ emoluments are incl

Sheet Review Queue 待覆核
A1: 需要人手處理的項目
A2: 工具沒抓到的東西會列在這裡,不會靜靜消失 —— 請人手翻閱原文補入。
A4: 一、未擷取到的財務科目
A5: 可能原因:該公司未單獨揭露此科目 / 用了工具不認得的措辭 / 位於跨頁或附註中。措辭問題可在 config.py 補上別名。
A7: 報表 Statement | B7: 未擷取科目 Missing item
A8: Income Statement | B8: Operating Profit
A9: Income Statement | B9: R&D Expenses
A10: Income Statement | B10: Depreciation
A11: Income Statement | B11: Amortisation
A12: Balance Sheet | B12: Total Assets
A13: Balance Sheet | B13: Intangible Assets
A14: Balance Sheet | B14: Investment Properties
A15: Balance Sheet | B15: Total Liabilities
A16: Balance Sheet | B16: Borrowings
A17: Cash Flow | B17: Investing Cash Flow
A18: Cash Flow | B18: Capital Expenditure
A21: 二、文字量過低的頁面(疑似掃描頁)
A22: 這些頁面幾乎抓不到文字,通常是掃描件或純圖表,建議人手翻閱或另行 OCR。
A24: PDF 頁碼 | B24: 狀態
A25: 1 | B25: 文字量過低 — 可能為掃描頁/圖表頁
A26: 142 | B26: 文字量過低 — 可能為掃描頁/圖表頁
