Workbook

Sheet Summary 摘要
A1: HKEX 文件資料萃取報告
A2: Automated Extraction Report — Business Valuation Support
A4: 來源文件 Source file | B4: sample_annual_report.pdf
A5: 產生時間 Generated | B5: 2026-08-28 15:49
A7: 總頁數 Total pages | B7: 12
A8: 已擷取字元 Characters extracted | B8: 5873
A9: 含表格頁數 Pages with tables | B9: 0
A10: 需人手/OCR 頁數 Pages needing OCR | B10: 1
A12: 估值參數擷取筆數 Valuation parameters | B12: 10
A13: 財務科目擷取筆數 Financial line items | B13: 28
A14: 主題段落擷取筆數 Topic extracts | B14: 14
A15: AI 複核筆數 AI-verified findings | B15: 0
A17: 方法論 Methodology
A18: 1. 逐頁擷取文字,全程保留 PDF 頁碼與年報印刷頁碼(可追溯性)。
A19: 2. 規則層(正則/關鍵字)先把全份文件縮減為少數相關頁面 —— 解決「文件太大」。
A20: 3. 數字由正則精確擷取並做合理性檢查,不由語言模型生成 —— 解決「準確度」。
A21: 4. AI 僅在縮減後的頁面上做語意判斷,且輸出頁碼須通過驗證才保留。
A22: 5. 所有結果附來源頁碼,供估值師覆核。信心度為 Low 者建議人手確認。

Sheet Valuation Params 估值參數
A1: 估值參數 Benchmark — 可直接併入行內參數資料庫
A2: 數字由正則式從原文精確擷取,並經合理範圍檢查;非由 AI 生成。
A4: 參數 Parameter | B4: 中文 | C4: 下限 Low (%) | D4: 上限 High (%) | E4: 原文數值 | F4: 信心度 | G4: 來源頁 Source Page | H4: 上下文 Context
A5: Capitalisation Rate | B5: 資本化率 | C5: 3.8 | D5: 3.8 | E5: 3.8% | F5: High | G5: PDF p.11 (印刷頁 64) | H5: e valuation was arrived at using the income capitalisation approach, adopting a capitalisation rate of 3.8% (2023: 4.0%) for the retail portion and a capitalisation rate of 4.5% for the office portion. The fair value measurement is categorised within Level 3
A6: Capitalisation Rate | B6: 資本化率 | C6: 4.5 | D6: 4.5 | E6: 4.5% | F6: High | G6: PDF p.11 (印刷頁 64) | H6: dopting a capitalisation rate of 3.8% (2023: 4.0%) for the retail portion and a capitalisation rate of 4.5% for the office portion. The fair value measurement is categorised within Level 3 of the fair value hierarchy. Significant unobservable inputs include t
A7: Discount Rate | B7: 折現率 | C7: 15.5 | D7: 15.5 | E7: 15.5% | F7: High | G7: PDF p.9 (印刷頁 58) | H7: the Manufacturing CGU is 13.2% (2023: 12.8%). For the Technology CGU, a pre-tax discount rate of 15.5% was applied. Cash flows beyond the five-year period are extrapolated using a terminal growth rate of 2.5%, which does not exceed the long-term average
A8: Discount Rate | B8: 折現率 | C8: 13.2 | D8: 13.2 | E8: 13.2% | F8: Medium | G8: PDF p.9 (印刷頁 58) | H8: low projections covering a five-year period approved by management. The pre-tax discount rate applied to the cash flow projections of the Manufacturing CGU is 13.2% (2023: 12.8%). For the Technology CGU, a pre-tax discount rate of 15.5% was applied. Cas
A9: Discount Rate | B9: 折現率 | C9: 14 | D9: 14 | E9: 14.0% | F9: High | G9: PDF p.10 (印刷頁 61) | H9: he recoverable amount was determined using the relief-fromroyalty method with a discount rate of 14.0% and a notional royalty rate of 3.0% of revenue. 61
A10: Expected Volatility | B10: 預期波幅 | C10: 42 | D10: 42 | E10: 42.0% | F10: High | G10: PDF p.12 (印刷頁 70) | H10: he year was determined using the binomial model, with the following key inputs: Expected volatility of 42.0% Risk-free rate of 3.6% Expected dividend yield of 1.8% Expected option life of 6 years 30. RELATED PARTY TRANSACTIONS During the year the Group entere
A11: Gross Margin | B11: 毛利率 | C11: 38.5 | D11: 38.5 | E11: 38.5% | F11: High | G11: PDF p.3 (印刷頁 1) | H11: of HK$1,284,500,000, representing an increase of 12.4% over the prior year. The gross profit margin was 38.5% (2023: 36.2%), driven by an improved product mix. The Company holds a 51% equity interest in Sample Technology Limited, which remains its principal o
A12: Risk-free Rate | B12: 無風險利率 | C12: 3.6 | D12: 3.6 | E12: 3.6% | F12: High | G12: PDF p.12 (印刷頁 70) | H12: the binomial model, with the following key inputs: Expected volatility of 42.0% Risk-free rate of 3.6% Expected dividend yield of 1.8% Expected option life of 6 years 30. RELATED PARTY TRANSACTIONS During the year the Group entered into connected transac
A13: Terminal Growth Rate | B13: 永續增長率 | C13: 2.5 | D13: 2.5 | E13: 2.5% | F13: High | G13: PDF p.9 (印刷頁 58) | H13: 5% was applied. Cash flows beyond the five-year period are extrapolated using a terminal growth rate of 2.5%, which does not exceed the long-term average growth rate of the industry in which each CGU operates. The weighted average cost of capital used in
A14: WACC | B14: 加權平均資本成本 | C14: 11.8 | D14: 11.8 | E14: 11.8% | F14: High | G14: PDF p.9 (印刷頁 58) | H14: e long-term average growth rate of the industry in which each CGU operates. The weighted average cost of capital used in the assessment was 11.8%. Management determined that a reasonably possible change in the discount rate of 100 basis points would not result in an impai

Sheet Financials 財務數據
A1: 三大報表擷取結果
A2: 偵測到的年度欄位 — Income Statement: 2024 / 2023; Balance Sheet: 2024 / 2023; Cash Flow: 2024 / 2023
A4: 報表 Statement | B4: 科目 Item | C4: 本年 Current | D4: 上年 Prior | E4: 變動 YoY % | F4: 來源頁 | G4: 原文行 Source line
A5: Income Statement | B5: Revenue | C5: 1284500 | D5: 1142800 | E5: =IFERROR(IF(D5=0,"",(C5-D5)/ABS(D5)),"") -> 0.1239937 | F5: PDF p.6 (印刷頁 20) | G5: Revenue 5 1,284,500 1,142,800
A6: Income Statement | B6: Cost of Sales | C6: -789967 | D6: -729105 | E6: =IFERROR(IF(D6=0,"",(C6-D6)/ABS(D6)),"") -> -0.083474945 | F6: PDF p.6 (印刷頁 20) | G6: Cost of sales (789,967) (729,105)
A7: Income Statement | B7: Gross Profit | C7: 494533 | D7: 413695 | E7: =IFERROR(IF(D7=0,"",(C7-D7)/ABS(D7)),"") -> 0.19540483 | F7: PDF p.6 (印刷頁 20) | G7: Gross profit 494,533 413,695
A8: Income Statement | B8: R&D Expenses | C8: -96340 | D8: -78110 | E8: =IFERROR(IF(D8=0,"",(C8-D8)/ABS(D8)),"") -> -0.23338881 | F8: PDF p.6 (印刷頁 20) | G8: Research and development expenses 7 (96,340) (78,110)
A9: Income Statement | B9: Operating Profit | C9: 85183 | D9: 51905 | E9: =IFERROR(IF(D9=0,"",(C9-D9)/ABS(D9)),"") -> 0.64113284 | F9: PDF p.6 (印刷頁 20) | G9: Operating profit 85,183 51,905
A10: Income Statement | B10: Finance Costs | C10: -18940 | D10: -21330 | E10: =IFERROR(IF(D10=0,"",(C10-D10)/ABS(D10)),"") -> 0.11204876 | F10: PDF p.6 (印刷頁 20) | G10: Finance costs 8 (18,940) (21,330)
A11: Income Statement | B11: Profit Before Tax | C11: 66243 | D11: 30575 | E11: =IFERROR(IF(D11=0,"",(C11-D11)/ABS(D11)),"") -> 1.166574 | F11: PDF p.6 (印刷頁 20) | G11: Profit before tax 66,243 30,575
A12: Income Statement | B12: Income Tax | C12: -14120 | D12: -6880 | E12: =IFERROR(IF(D12=0,"",(C12-D12)/ABS(D12)),"") -> -1.0523256 | F12: PDF p.6 (印刷頁 20) | G12: Income tax expense 9 (14,120) (6,880)
A13: Income Statement | B13: Profit for the Year | C13: 52123 | D13: 23695 | E13: =IFERROR(IF(D13=0,"",(C13-D13)/ABS(D13)),"") -> 1.1997468 | F13: PDF p.6 (印刷頁 20) | G13: Profit for the year 52,123 23,695
A14: Income Statement | B14: Depreciation | C14: 64210 | D14: 58940 | E14: =IFERROR(IF(D14=0,"",(C14-D14)/ABS(D14)),"") -> 0.089412962 | F14: PDF p.6 (印刷頁 20) | G14: Depreciation 64,210 58,940
A15: Income Statement | B15: Amortisation | C15: 19880 | D15: 16220 | E15: =IFERROR(IF(D15=0,"",(C15-D15)/ABS(D15)),"") -> 0.22564735 | F15: PDF p.6 (印刷頁 20) | G15: Amortisation 19,880 16,220
A16: Balance Sheet | B16: Property Plant and Equipment | C16: 618440 | D16: 591220 | E16: =IFERROR(IF(D16=0,"",(C16-D16)/ABS(D16)),"") -> 0.046040391 | F16: PDF p.7 (印刷頁 22) | G16: Property, plant and equipment 12 618,440 591,220
... A32: Cash Flow | B32: Financing Cash Flow | C32: -12050 | D32: -34610 | E32: =IFERROR(IF(D32=0,"",(C32-D32)/ABS(D32)),"") -> 0.65183473 | F32: PDF p.8 (印刷頁 24) | G32: Net cash used in financing activities (12,050) (34,610)
A34: 藍色 = 從 PDF 原文擷取的數值(硬輸入);黑色 = 公式計算。單位依原報表所示(通常為千元或百萬元),請對照來源頁確認。

Sheet Ratios 財務比率
A1: 衍生比率 — 全部以公式連結至 Financials 分頁
A2: 改動 Financials 分頁的數字,本頁會自動重算。
A4: 比率 Ratio | B4: 本年 Current | C4: 上年 Prior | D4: 說明
A5: Gross Margin 毛利率 | B5: =IFERROR(IFERROR(INDEX('Financials 財務數據'!$C$5:$C$32,MATCH("Gross Profit",'Financials 財務數據'!$B$5:$B$32,0)),"")/IFERROR(INDEX('Financials 財務數據'!$C$5:$C$32,MATCH("Revenue",'Financials 財務數據'!$B$5:$B$32,0)),""),"n/a") -> 0.38500039 | C5: =IFERROR(IFERROR(INDEX('Financials 財務數據'!$D$5:$D$32,MATCH("Gross Profit",'Financials 財務數據'!$B$5:$B$32,0)),"")/IFERROR(INDEX('Financials 財務數據'!$D$5:$D$32,MATCH("Revenue",'Financials 財務數據'!$B$5:$B$32,0)),""),"n/a") -> 0.36200123 | D5: 毛利 ÷ 收入
A6: Net Margin 淨利率 | B6: =IFERROR(IFERROR(INDEX('Financials 財務數據'!$C$5:$C$32,MATCH("Profit for the Year",'Financials 財務數據'!$B$5:$B$32,0)),"")/IFERROR(INDEX('Financials 財務數據'!$C$5:$C$32,MATCH("Revenue",'Financials 財務數據'!$B$5:$B$32,0)),""),"n/a") -> 0.040578435 | C6: =IFERROR(IFERROR(INDEX('Financials 財務數據'!$D$5:$D$32,MATCH("Profit for the Year",'Financials 財務數據'!$B$5:$B$32,0)),"")/IFERROR(INDEX('Financials 財務數據'!$D$5:$D$32,MATCH("Revenue",'Financials 財務數據'!$B$5:$B$32,0)),""),"n/a") -> 0.020734162 | D6: 年內溢利 ÷ 收入
A7: Current Ratio 流動比率 | B7: =IFERROR(IFERROR(INDEX('Financials 財務數據'!$C$5:$C$32,MATCH("Total Current Assets",'Financials 財務數據'!$B$5:$B$32,0)),"")/IFERROR(INDEX('Financials 財務數據'!$C$5:$C$32,MATCH("Total Current Liabilities",'Financials 財務數據'!$B$5:$B$32,0)),""),"n/a") -> 1.6120331 | C7: =IFERROR(IFERROR(INDEX('Financials 財務數據'!$D$5:$D$32,MATCH("Total Current Assets",'Financials 財務數據'!$B$5:$B$32,0)),"")/IFERROR(INDEX('Financials 財務數據'!$D$5:$D$32,MATCH("Total Current Liabilities",'Financials 財務數據'!$B$5:$B$32,0)),""),"n/a") -> 1.3827193 | D7: 流動資產 ÷ 流動負債
A8: Debt / Equity 負債權益比 | B8: =IFERROR(IFERROR(INDEX('Financials 財務數據'!$C$5:$C$32,MATCH("Total Liabilities",'Financials 財務數據'!$B$5:$B$32,0)),"")/IFERROR(INDEX('Financials 財務數據'!$C$5:$C$32,MATCH("Total Equity",'Financials 財務數據'!$B$5:$B$32,0)),""),"n/a") -> 0.70954223 | C8: =IFERROR(IFERROR(INDEX('Financials 財務數據'!$D$5:$D$32,MATCH("Total Liabilities",'Financials 財務數據'!$B$5:$B$32,0)),"")/IFERROR(INDEX('Financials 財務數據'!$D$5:$D$32,MATCH("Total Equity",'Financials 財務數據'!$B$5:$B$32,0)),""),"n/a") -> 0.92170073 | D8: 總負債 ÷ 總權益
A9: Goodwill / Total Assets | B9: =IFERROR(IFERROR(INDEX('Financials 財務數據'!$C$5:$C$32,MATCH("Goodwill",'Financials 財務數據'!$B$5:$B$32,0)),"")/IFERROR(INDEX('Financials 財務數據'!$C$5:$C$32,MATCH("Total Assets",'Financials 財務數據'!$B$5:$B$32,0)),""),"n/a") -> 0.1004857 | C9: =IFERROR(IFERROR(INDEX('Financials 財務數據'!$D$5:$D$32,MATCH("Goodwill",'Financials 財務數據'!$B$5:$B$32,0)),"")/IFERROR(INDEX('Financials 財務數據'!$D$5:$D$32,MATCH("Total Assets",'Financials 財務數據'!$B$5:$B$32,0)),""),"n/a") -> 0.10612304 | D9: 商譽佔總資產比重 — 減值風險指標
A10: Intangibles / Total Assets | B10: =IFERROR(IFERROR(INDEX('Financials 財務數據'!$C$5:$C$32,MATCH("Intangible Assets",'Financials 財務數據'!$B$5:$B$32,0)),"")/IFERROR(INDEX('Financials 財務數據'!$C$5:$C$32,MATCH("Total Assets",'Financials 財務數據'!$B$5:$B$32,0)),""),"n/a") -> 0.072972794 | C10: =IFERROR(IFERROR(INDEX('Financials 財務數據'!$D$5:$D$32,MATCH("Intangible Assets",'Financials 財務數據'!$B$5:$B$32,0)),"")/IFERROR(INDEX('Financials 財務數據'!$D$5:$D$32,MATCH("Total Assets",'Financials 財務數據'!$B$5:$B$32,0)),""),"n/a") -> 0.070874551 | D10: 無形資產佔比
A11: ROE 股本回報率 | B11: =IFERROR(IFERROR(INDEX('Financials 財務數據'!$C$5:$C$32,MATCH("Profit for the Year",'Financials 財務數據'!$B$5:$B$32,0)),"")/IFERROR(INDEX('Financials 財務數據'!$C$5:$C$32,MATCH("Total Equity",'Financials 財務數據'!$B$5:$B$32,0)),""),"n/a") -> 0.045509155 | C11: =IFERROR(IFERROR(INDEX('Financials 財務數據'!$D$5:$D$32,MATCH("Profit for the Year",'Financials 財務數據'!$B$5:$B$32,0)),"")/IFERROR(INDEX('Financials 財務數據'!$D$5:$D$32,MATCH("Total Equity",'Financials 財務數據'!$B$5:$B$32,0)),""),"n/a") -> 0.024560512 | D11: 年內溢利 ÷ 總權益
A13: 顯示 "n/a" 表示該科目未在文件中成功擷取,需人手補入。

Sheet Chart 趨勢圖
A1: 本年 vs 上年 — 主要科目比較
A2: 港交所主板及 GEM 自 2024 年起均無強制季度報告,故以年度 / 中期數據作趨勢比較較符合披露實況。
A4: Item | B4: Prior | C4: Current
A5: Revenue | B5: 1142800 | C5: 1284500
A6: Gross Profit | B6: 413695 | C6: 494533
A7: Profit Before Tax | B7: 30575 | C7: 66243
A8: Profit for the Year | B8: 23695 | C8: 52123
A9: Total Assets | B9: 1853980 | C9: 1957990
A10: Total Equity | B10: 964760 | C10: 1145330

Sheet Extracts 主題段落
A1: 主題式段落擷取 — 供估值師快速定位原文
A3: 主題 Topic | B3: 中文 | C3: 優先 | D3: 命中詞 | E3: 來源頁 | F3: 段落 Snippet
A4: Fair Value Measurement | B4: 公允價值計量 | C4: high | D4: level 3 | E4: PDF p.11 (印刷頁 64) | F4: %) for the retail portion and a capitalisation rate of 4.5% for the office portion. The fair value measurement is categorised within Level 3 of the fair value hierarchy. Significant unobservable inputs include the market rent of HK$52 per square foot per month and the capitalisation rate. The total gross floor area of the investment properties is 128,400 square feet. 64
A5: Impairment Testing | B5: 減值測試 | C5: high | D5: impairment test | E5: PDF p.9 (印刷頁 58) | F5: L STATEMENTS 14. GOODWILL Goodwill acquired through business combinations has been allocated to two cash-generating units (CGUs) for impairment testing. The recoverable amount of each CGU has been determined based on a value in use calculation using cash flow projections covering a five-year period approved by management. The pre-tax discount rate applied to the cash flow projections of the Manufacturing CGU is 13.2% (2023: 12.8%). For the Technology CGU, a pre-tax discount rate of 15.5% was applied. Cash flows beyond the five-
A6: Impairment Testing | B6: 減值測試 | C6: high | D6: recoverable amount | E6: PDF p.10 (印刷頁 61) | F6: pment costs 5 years Trademarks Indefinite useful life Trademarks with indefinite useful life are tested for impairment annually. The recoverable amount was determined using the relief-fromroyalty method with a discount rate of 14.0% and a notional royalty rate of 3.0% of revenue. 61
A7: Intangible Assets & Goodwill | B7: 無形資產及商譽 | C7: high | D7: intangible asset | E7: PDF p.3 (印刷頁 1) | F7: HK$96,340,000 (2023: HK$78,110,000), representing 7.5% of revenue. Capitalised development costs of HK$22,400,000 were recognised as intangible assets during the year. 1
A8: Intangible Assets & Goodwill | B8: 無形資產及商譽 | C8: high | D8: amortisation | E8: PDF p.6 (印刷頁 20) | F8: ) Profit before tax 66,243 30,575 Income tax expense 9 (14,120) (6,880) Profit for the year 52,123 23,695 Depreciation 64,210 58,940 Amortisation 19,880 16,220 20
A9: Intangible Assets & Goodwill | B9: 無形資產及商譽 | C9: high | D9: intangible asset | E9: PDF p.7 (印刷頁 22) | F9: current assets Property, plant and equipment 12 618,440 591,220 Investment properties 13 284,000 262,000 Goodwill 14 196,750 196,750 Intangible assets 15 142,880 131,400 Total non-current assets 1,242,070 1,181,370 Current assets Inventories 16 218,340 241,880 Trade and other receivables 17 312,660 288,420 Cash and cash equivalents 18 184,920 142,310 Total current assets 715,920 672,610 Total assets 1,957,990 1,853,980 Current liabilities Trade and other payables 19 248,110 262,440 Bank borrowings 20 196,000 224,000 Total curre
A10: Intangible Assets & Goodwill | B10: 無形資產及商譽 | C10: high | D10: goodwill | E10: PDF p.9 (印刷頁 58) | F10: NOTES TO THE CONSOLIDATED FINANCIAL STATEMENTS 14. GOODWILL Goodwill acquired through business combinations has been allocated to two cash-generating units (CGUs) for impairment testing. The recoverable amount of each CGU has been determined based on a value in use calculation using cash flow projections covering a five-year period approved by management. The pre-tax discount rate applied to the cash flow projections of the Manufacturing CGU is 13
A11: Intangible Assets & Goodwill | B11: 無形資產及商譽 | C11: high | D11: intangible asset | E11: PDF p.10 (印刷頁 61) | F11: 15. INTANGIBLE ASSETS Customer Development Relationships Costs Trademarks HK$'000 HK$'000 HK$'000 Cost at 1 January 84,200 112,600 41,500 Additions - 22,400 - Cost at 31 December 84,200 135,000 41,500 The useful lives of intangible assets are as follows: Customer relationships 10 years, amortised on a straight-line basis Development costs 5 years Trademarks Indefinite useful life Trademarks with indef
A12: Investment Properties | B12: 投資物業 | C12: high | D12: capitalisation rate | E12: PDF p.11 (印刷頁 64) | F12: t professional valuer, on the basis of fair value. The valuation was arrived at using the income capitalisation approach, adopting a capitalisation rate of 3.8% (2023: 4.0%) for the retail portion and a capitalisation rate of 4.5% for the office portion. The fair value measurement is categorised within Level 3 of the fair value hierarchy. Significant unobservable inputs include the market rent of HK$52 per square foot per month and the capitalisation rate. The total gross floor area of the investment properties is 128,400 squar
A13: ESG Data | B13: 環境社會及管治數據 | C13: medium | D13: greenhouse gas | E13: PDF p.4 (印刷頁 2) | F13: ENVIRONMENTAL, SOCIAL AND GOVERNANCE REPORT Emissions Scope 1 greenhouse gas emissions 12,480 tCO2e Scope 2 greenhouse gas emissions 34,910 tCO2e Total GHG emissions 47,390 tCO2e Emission intensity 0.037 tCO2e per HK$'000 revenue Energy Total energy consumption 68,220 MWh Renewable energy accounted for 18.0% of total consumption. The Group targets a 25% reduction in carbon intensity by 2030. 2
A14: R&D Expenditure | B14: 研發開支 | C14: medium | D14: research and development | E14: PDF p.3 (印刷頁 1) | F14: product mix. The Company holds a 51% equity interest in Sample Technology Limited, which remains its principal operating subsidiary. Research and Development Research and development expenditure for the year amounted to HK$96,340,000 (2023: HK$78,110,000), representing 7.5% of revenue. Capitalised development costs of HK$22,400,000 were recognised as intangible assets during the year. 1
... A17: Related Party Transactions | B17: 關聯方交易 | C17: low | D17: related party | E17: PDF p.12 (印刷頁 70) | F17: key inputs: Expected volatility of 42.0% Risk-free rate of 3.6% Expected dividend yield of 1.8% Expected option life of 6 years 30. RELATED PARTY TRANSACTIONS During the year the Group entered into connected transactions with a company controlled by a director amounting to HK$8,420,000. 70

Sheet Review Queue 待覆核
A1: 需要人手處理的頁面
A2: 這些頁面幾乎抓不到文字,通常是掃描件或純圖表,建議人手翻閱或另行 OCR。
A4: PDF 頁碼 | B4: 狀態
A5: 5 | B5: 文字量過低 — 可能為掃描頁/圖表頁
